{"Source":"InternalBuild","Data":{"System.CollectionId":"ace28d09-cee5-450f-bc2b-e4e8ed9728cb","System.DefinitionId":"36","System.TeamProjectId":"45567ab5-ee74-48b5-af9c-adb84e7b2590","System.TeamProject":"PowerShellEditorServices","Build.BuildId":"18241","Build.BuildNumber":"Release-release-20240104.01","Build.DefinitionName":"PowerShellEditorServices","Build.DefinitionRevision":"2","Build.Repository.Name":"PowerShellEditorServices","Build.Repository.Provider":"TfsGit","Build.Repository.Id":"03a08e59-1706-404c-9f88-832c1f0defdb","Build.SourceBranch":"refs/heads/release","Build.SourceBranchName":"release","Build.SourceVersion":"3698e548847831293baa78e7f563769215b3809a","Build.Repository.Uri":"https://dev.azure.com/powershell-rel/PowerShellEditorServices/_git/PowerShellEditorServices"},"Feed":null}